{"product":"yak.fish","updatedAt":"2026-07-19T11:57:55.247Z","degraded":false,"windowHours":26,"floodCapPerSource":12,"storyCount":163,"multiSourceCount":0,"recordCount":164,"cappedFromRecords":240,"floodOverflow":76,"sections":["COURTS","HEALTH","LOCAL","MONEY","POLITICS","SCIENCE","TECH","TOP","US","WAR","WORLD"],"stories":[{"id":"07bb333f24566d67","headline":"US and Iran exchange strikes after two US soldiers killed in Jordan","time":"2026-07-19T11:57:10.000Z","section":"TOP","sources":[{"name":"BBC — Top Stories","host":"bbc.co.uk","url":"https://bbc.co.uk/news/articles/cgk417jp83po?at_medium=RSS&at_campaign=rss","time":"2026-07-19T11:57:10.000Z"}]},{"id":"f6c0420dca00867f","headline":"World Cup 2026: Spain v Argentina final buildup; England win 10-goal thriller – live","time":"2026-07-19T11:48:16.000Z","section":"US","sources":[{"name":"The Guardian — U.S.","host":"theguardian.com","url":"https://theguardian.com/football/live/2026/jul/19/world-cup-2026-spain-v-argentina-final-buildup-england-win-10-goal-thriller-live","time":"2026-07-19T11:48:16.000Z"}]},{"id":"214ea513994beae8","headline":"South East Water supply disruption hits thousands of properties in Kent","time":"2026-07-19T11:46:19.000Z","section":"WORLD","sources":[{"name":"The Guardian — World","host":"theguardian.com","url":"https://theguardian.com/uk-news/2026/jul/19/south-east-water-supply-disruption-tunbridge-wells-kent","time":"2026-07-19T11:46:19.000Z"}]},{"id":"33bafd6e9d828d30","headline":"U.S. says it targeted Iranian forces after attacks that killed two American service members","time":"2026-07-19T11:36:45.000Z","section":"MONEY","sources":[{"name":"CNBC — Business","host":"cnbc.com","url":"https://cnbc.com/2026/07/19/us-says-it-targeted-iran-forces-after-deaths-of-two-american-troops.html","time":"2026-07-19T11:36:45.000Z"}]},{"id":"73ecaac021a4f0ea","headline":"From coffee grounds to guinea pig bedding - the composters keeping it local","time":"2026-07-19T11:33:19.000Z","section":"SCIENCE","sources":[{"name":"BBC — Science & Environment","host":"bbc.co.uk","url":"https://bbc.co.uk/news/articles/c78y2q6ve04o?at_medium=RSS&at_campaign=rss","time":"2026-07-19T11:33:19.000Z"}]},{"id":"95cbd2b8d5f5dc9d","headline":"Russia launches major ballistic missile attack on Ukrainian cities","time":"2026-07-19T11:28:24.000Z","section":"TOP","sources":[{"name":"BBC — Top Stories","host":"bbc.co.uk","url":"https://bbc.co.uk/news/articles/c2el7xpnzrpo?at_medium=RSS&at_campaign=rss","time":"2026-07-19T11:28:24.000Z"}]},{"id":"87e3f2e44c2b203a","headline":"The U.S. Braced For the World Cup. It Fell in Love Instead.","time":"2026-07-19T11:28:19.000Z","section":"WORLD","sources":[{"name":"The New York Times — World","host":"nytimes.com","url":"https://nytimes.com/2026/07/19/world/europe/us-world-cup-trump-boston-kansas.html","time":"2026-07-19T11:28:19.000Z"}]},{"id":"ab5ddca039b5f7c1","headline":"FIFA World Cup: Tobin Heath on record goals, France and Lamine Yamal","time":"2026-07-19T11:21:52.000Z","section":"WORLD","sources":[{"name":"Al Jazeera — All","host":"aljazeera.com","url":"https://aljazeera.com/sports/2026/7/19/tobin-heath-fifa-world-cup-2026-football-analysis-players-teams-tournament?traffic_source=rss","time":"2026-07-19T11:21:52.000Z"}]},{"id":"3850f33e8fbda70d","headline":"Guyana ferry with 116 people on board capsizes; more than 50 rescued","time":"2026-07-19T11:18:17.000Z","section":"WORLD","sources":[{"name":"Al Jazeera — All","host":"aljazeera.com","url":"https://aljazeera.com/news/2026/7/19/guyana-ferry-with-116-people-aboard-capsizes?traffic_source=rss","time":"2026-07-19T11:18:17.000Z"}]},{"id":"31f3d7e6c50327da","headline":"Iranians suffer from power blackouts during war and heatwave","time":"2026-07-19T11:16:20.000Z","section":"WORLD","sources":[{"name":"Al Jazeera — All","host":"aljazeera.com","url":"https://aljazeera.com/news/2026/7/19/iranians-suffer-from-power-blackouts-during-war-and-heatwave?traffic_source=rss","time":"2026-07-19T11:16:20.000Z"}]},{"id":"a8f4e17212237e7d","headline":"Burnham will be bolder but stick to Labour manifesto, deputy leader says","time":"2026-07-19T11:15:51.000Z","section":"TOP","sources":[{"name":"BBC — Top Stories","host":"bbc.co.uk","url":"https://bbc.co.uk/news/articles/cx2k76gydreo?at_medium=RSS&at_campaign=rss","time":"2026-07-19T11:15:51.000Z"}]},{"id":"23c3e3078c2489a1","headline":"Middle East crisis live: US launches new round of airstrikes to ‘swiftly punish’ Iran after American troops killed","time":"2026-07-19T11:15:30.000Z","section":"WORLD","sources":[{"name":"The Guardian — World","host":"theguardian.com","url":"https://theguardian.com/world/live/2026/jul/19/middle-east-crisis-live-us-launches-new-round-of-airstrikes-to-swiftly-punish-iran-after-american-troops-killed","time":"2026-07-19T11:15:30.000Z"}]},{"id":"1b788e7cf1dc7e4c","headline":"Shark scientists gets £1m to help protect them","time":"2026-07-19T11:11:57.000Z","section":"SCIENCE","sources":[{"name":"BBC — Science & Environment","host":"bbc.co.uk","url":"https://bbc.co.uk/news/articles/cly9yyj829ro?at_medium=RSS&at_campaign=rss","time":"2026-07-19T11:11:57.000Z"}]},{"id":"a4e0df3ffd7b7d92","headline":"Tate brothers arrested in US as further UK charges take total to 59","time":"2026-07-19T11:04:50.000Z","section":"TOP","sources":[{"name":"BBC — Top Stories","host":"bbc.co.uk","url":"https://bbc.co.uk/news/articles/cwymly9yd33o?at_medium=RSS&at_campaign=rss","time":"2026-07-19T11:04:50.000Z"}]},{"id":"449f026dc7c6b81f","headline":"Politicians condemn 'disgraceful' scenes of 'absolute chaos'","time":"2026-07-19T11:00:50.000Z","section":"WORLD","sources":[{"name":"BBC — UK","host":"bbc.co.uk","url":"https://bbc.co.uk/news/articles/c8enkde2lnyo?at_medium=RSS&at_campaign=rss","time":"2026-07-19T11:00:50.000Z"}]},{"id":"8d1515769531dcd1","headline":"Trump is invoking foreign election interference to justify his own | Jamil Smith","time":"2026-07-19T11:00:27.000Z","section":"US","sources":[{"name":"The Guardian — U.S.","host":"theguardian.com","url":"https://theguardian.com/commentisfree/2026/jul/19/trump-foreign-election-interference","time":"2026-07-19T11:00:27.000Z"}]},{"id":"cfc0e758bce88b9f","headline":"U.S. Launches Strikes After Iranian Attack Kills 2 American Soldiers","time":"2026-07-19T11:00:27.000Z","section":"WORLD","sources":[{"name":"The New York Times — World","host":"nytimes.com","url":"https://nytimes.com/live/2026/07/18/world/iran-war-strikes-trump-hormuz","time":"2026-07-19T11:00:27.000Z"}]},{"id":"78dab5a5dffcbfb6","headline":"Molten salt and human sweat: the weird batteries that could store renewable energy","time":"2026-07-19T11:00:25.000Z","section":"WORLD","sources":[{"name":"The Guardian — World","host":"theguardian.com","url":"https://theguardian.com/environment/2026/jul/19/molten-salt-human-sweat-weird-batteries-store-renewable-energy","time":"2026-07-19T11:00:25.000Z"}]},{"id":"f27395c4a4369b1a","headline":"How Trump and his administration have mired the US in multiple crises","time":"2026-07-19T11:00:25.000Z","section":"US","sources":[{"name":"The Guardian — U.S.","host":"theguardian.com","url":"https://theguardian.com/us-news/2026/jul/19/how-trump-and-his-administration-have-mired-the-us-in-multiple-crises","time":"2026-07-19T11:00:25.000Z"}]},{"id":"b8f24f02d6f8d2fe","headline":"Could AI be conscious?","time":"2026-07-19T11:00:25.000Z","section":"TECH","sources":[{"name":"The Guardian — Technology","host":"theguardian.com","url":"https://theguardian.com/technology/2026/jul/19/could-ai-be-conscious","time":"2026-07-19T11:00:25.000Z"}]},{"id":"0a83d44f5615aaa8","headline":"Deaths of 2 U.S. Troops in Jordan Brings American Toll in the War With Iran to 16","time":"2026-07-19T11:00:25.000Z","section":"WORLD","sources":[{"name":"The New York Times — World","host":"nytimes.com","url":"https://nytimes.com/2026/07/18/world/middleeast/us-troops-killed-iran-war-jordan.html","time":"2026-07-19T11:00:25.000Z"}]},{"id":"d9dbeccb4a75c92b","headline":"Britain set for butterfly boom after hot spring","time":"2026-07-19T11:00:13.000Z","section":"SCIENCE","sources":[{"name":"BBC — Science & Environment","host":"bbc.co.uk","url":"https://bbc.co.uk/news/articles/crrv5lw7017o?at_medium=RSS&at_campaign=rss","time":"2026-07-19T11:00:13.000Z"}]},{"id":"e18246345253ea24","headline":"Violence repeatedly erupts in dementia care despite warnings, inspections show","time":"2026-07-19T11:00:00.000Z","section":"TOP","sources":[{"name":"NPR — News","host":"npr.org","url":"https://npr.org/2026/07/19/nx-s1-5894692/dementia-violence-warning-supervision-nursing-homes-assisted-living-facility","time":"2026-07-19T11:00:00.000Z"}]},{"id":"2f21cdb13501a69c","headline":"Chinese firm seeks compensation over British Steel nationalisation","time":"2026-07-19T10:59:07.000Z","section":"TOP","sources":[{"name":"BBC — Top Stories","host":"bbc.co.uk","url":"https://bbc.co.uk/news/articles/cwyj4ppqn41o?at_medium=RSS&at_campaign=rss","time":"2026-07-19T10:59:07.000Z"}]},{"id":"4b9eda444bb96a71","headline":"Russia Batters Kyiv in One of the Largest Missile Assaults of the War","time":"2026-07-19T10:52:22.000Z","section":"WORLD","sources":[{"name":"The New York Times — World","host":"nytimes.com","url":"https://nytimes.com/2026/07/19/world/europe/russia-ukraine-strikes.html","time":"2026-07-19T10:52:22.000Z"}]},{"id":"4913cc5fb39d537b","headline":"Anger as water supply misery continues for second day","time":"2026-07-19T10:52:09.000Z","section":"WORLD","sources":[{"name":"BBC — UK","host":"bbc.co.uk","url":"https://bbc.co.uk/news/articles/ce3q128kn4qo?at_medium=RSS&at_campaign=rss","time":"2026-07-19T10:52:09.000Z"}]},{"id":"89b0ac204c6cfc47","headline":"Why is India vetting books in Kashmir in search of ‘anti-national’ content?","time":"2026-07-19T10:43:27.000Z","section":"WORLD","sources":[{"name":"Al Jazeera — All","host":"aljazeera.com","url":"https://aljazeera.com/news/2026/7/19/why-is-india-vetting-books-in-kashmir-in-search-of-anti-national-content?traffic_source=rss","time":"2026-07-19T10:43:27.000Z"}]},{"id":"fc362412ed3ae086","headline":"The Bayeux tapestry arrives in London for display at British Museum","time":"2026-07-19T10:33:33.000Z","section":"WORLD","sources":[{"name":"France 24 — English","host":"france24.com","url":"https://france24.com/en/the-bayeux-tapestry-arrives-in-london-for-display-at-british-museum","time":"2026-07-19T10:33:33.000Z"}]},{"id":"fb92c6a1709ec685","headline":"Ukraine: Thousands take to the streets to protest against Fedorov removal","time":"2026-07-19T10:31:43.000Z","section":"WORLD","sources":[{"name":"France 24 — English","host":"france24.com","url":"https://france24.com/en/ukraine-thousands-take-to-the-streets-to-protest-against-fedorov-removal","time":"2026-07-19T10:31:43.000Z"}]},{"id":"0606c6b542d36958","headline":"World Cup final: Argentina face Spain","time":"2026-07-19T10:25:33.000Z","section":"WORLD","sources":[{"name":"France 24 — English","host":"france24.com","url":"https://france24.com/en/world-cup-final-argentina-face-spain","time":"2026-07-19T10:25:33.000Z"}]},{"id":"3c15c2d0de24e720","headline":"🔴 Middle East live: Iran's Guards say two ships involved in 'accident' after defying Hormuz warnings","time":"2026-07-19T10:13:33.000Z","section":"WORLD","sources":[{"name":"France 24 — English","host":"france24.com","url":"https://france24.com/en/middle-east/20260719-middle-east-live-us-targets-iran-s-revolutionary-guard-in-retaliation-for-killed-troops","time":"2026-07-19T10:13:33.000Z"}]},{"id":"d871b3b6589ee37c","headline":"A final that will define Lamine Yamal's World Cup","time":"2026-07-19T10:11:29.000Z","section":"TOP","sources":[{"name":"BBC — Top Stories","host":"bbc.co.uk","url":"https://bbc.co.uk/sport/football/articles/cdx8r45w2gzo?at_medium=RSS&at_campaign=rss","time":"2026-07-19T10:11:29.000Z"}]},{"id":"c33f7952dbbd6f30","headline":"Gaza cheers for Spain as World Cup final anticipation mounts","time":"2026-07-19T10:09:25.000Z","section":"WORLD","sources":[{"name":"Al Jazeera — All","host":"aljazeera.com","url":"https://aljazeera.com/news/2026/7/19/gaza-cheers-for-spain-as-world-cup-final-anticipation-mounts?traffic_source=rss","time":"2026-07-19T10:09:25.000Z"}]},{"id":"88ea169e4a594dd2","headline":"‘White men get to fail’: Graham Platner collapse illuminates toxic double standard in US politics","time":"2026-07-19T10:00:23.000Z","section":"US","sources":[{"name":"The Guardian — U.S.","host":"theguardian.com","url":"https://theguardian.com/us-news/2026/jul/19/graham-platner-double-standard-politics","time":"2026-07-19T10:00:23.000Z"}]},{"id":"a39731c91a5f1c02","headline":"An Israeli paraglider tries to save migrating swifts that nest in the Western Wall","time":"2026-07-19T10:00:00.000Z","section":"TOP","sources":[{"name":"NPR — News","host":"npr.org","url":"https://npr.org/2026/07/19/nx-s1-5870684/israel-swift-birds-jerusalem","time":"2026-07-19T10:00:00.000Z"}]},{"id":"6418f176fd256e47","headline":"Ferry carrying 116 passengers sinks off Guyana coast, authorities say","time":"2026-07-19T09:59:41.000Z","section":"TOP","sources":[{"name":"BBC — Top Stories","host":"bbc.co.uk","url":"https://bbc.co.uk/news/articles/cm2gm99nrm7o?at_medium=RSS&at_campaign=rss","time":"2026-07-19T09:59:41.000Z"}]},{"id":"e1fc3b1b7849d095","headline":"Bad Bunny concert in Milan abandoned because of hailstorm","time":"2026-07-19T09:57:53.000Z","section":"WORLD","sources":[{"name":"The Guardian — World","host":"theguardian.com","url":"https://theguardian.com/music/2026/jul/19/bad-bunny-milan-abandoned-hailstorm","time":"2026-07-19T09:57:53.000Z"}]},{"id":"4ee073849b6eb09c","headline":"Messi on the brink of history - will it be his last World Cup game?","time":"2026-07-19T09:55:22.000Z","section":"TOP","sources":[{"name":"BBC — Top Stories","host":"bbc.co.uk","url":"https://bbc.co.uk/sport/football/articles/cql1xxxpndlo?at_medium=RSS&at_campaign=rss","time":"2026-07-19T09:55:22.000Z"}]},{"id":"f0206e81808d4912","headline":"Is Burnham promising a new dawn for North Sea oil and gas?","time":"2026-07-19T09:52:48.000Z","section":"WORLD","sources":[{"name":"BBC — UK","host":"bbc.co.uk","url":"https://bbc.co.uk/news/articles/c4g3l22ry6wo?at_medium=RSS&at_campaign=rss","time":"2026-07-19T09:52:48.000Z"}]},{"id":"08986b74e34166da","headline":"Has Saka shown Tuchel he's too good to leave out?","time":"2026-07-19T09:52:44.000Z","section":"TOP","sources":[{"name":"BBC — Top Stories","host":"bbc.co.uk","url":"https://bbc.co.uk/sport/football/articles/c0ejnwj0n4jo?at_medium=RSS&at_campaign=rss","time":"2026-07-19T09:52:44.000Z"}]},{"id":"631872748de60b4b","headline":"Argentina coach accuses England of lack of respect","time":"2026-07-19T09:47:34.000Z","section":"TOP","sources":[{"name":"BBC — Top Stories","host":"bbc.co.uk","url":"https://bbc.co.uk/sport/rugby-union/articles/cn4nvx0zxzqo?at_medium=RSS&at_campaign=rss","time":"2026-07-19T09:47:34.000Z"}]},{"id":"a10c9e59aee1f1c6","headline":"Du Plessis makes winning return to UFC with dominant decision over Usman","time":"2026-07-19T09:46:35.000Z","section":"WORLD","sources":[{"name":"Al Jazeera — All","host":"aljazeera.com","url":"https://aljazeera.com/sports/2026/7/19/dricus-du-plessis-mma-ufc-unanimous-decision-kamaru-usman?traffic_source=rss","time":"2026-07-19T09:46:35.000Z"}]},{"id":"e63d7e5e009c4483","headline":"At least 50 Malian soldiers killed in rebel-jihadist attack","time":"2026-07-19T09:44:32.000Z","section":"WORLD","sources":[{"name":"© AFP","host":"france24.com","url":"https://france24.com/en/africa/20260719-at-least-50-malian-soldiers-killed-in-rebel-jihadist-attack","time":"2026-07-19T09:44:32.000Z"}]},{"id":"165afb91462065ee","headline":"Wildfire scorches 12,000 hectares in central Spain's Guadalajara province","time":"2026-07-19T09:39:37.000Z","section":"WORLD","sources":[{"name":"© Military Emergencies Unit (UME) via AFP","host":"france24.com","url":"https://france24.com/en/europe/20260719-wildfire-scorches-12-000-hectares-in-central-spain-s-guadalajara-province","time":"2026-07-19T09:39:37.000Z"}]},{"id":"d070a614d79b0182","headline":"World Cup 2026 final: Closing ceremony and half-time show – what to know","time":"2026-07-19T09:35:52.000Z","section":"WORLD","sources":[{"name":"Al Jazeera — All","host":"aljazeera.com","url":"https://aljazeera.com/sports/2026/7/19/world-cup-2026-final-closing-ceremony-and-half-time-show-what-to-know?traffic_source=rss","time":"2026-07-19T09:35:52.000Z"}]},{"id":"662799fbacc270fe","headline":"Deadly overnight Russian attack on Ukraine targets the capital","time":"2026-07-19T09:14:38.000Z","section":"TOP","sources":[{"name":"NPR — News","host":"npr.org","url":"https://npr.org/2026/07/19/nx-s1-5899518/russia-attack-kyiv","time":"2026-07-19T09:14:38.000Z"}]},{"id":"1c9163ee6088b6f7","headline":"Five people rescued after Indonesia boat sinks, at least 20 still missing","time":"2026-07-19T09:08:55.000Z","section":"WORLD","sources":[{"name":"Al Jazeera — All","host":"aljazeera.com","url":"https://aljazeera.com/news/2026/7/19/five-people-rescued-after-indonesia-boat-sinks-at-least-20-still-missing?traffic_source=rss","time":"2026-07-19T09:08:55.000Z"}]},{"id":"9ce081a93517a55c","headline":"Argentines, Already ‘Losing Their Minds,’ Brace for World Cup Final","time":"2026-07-19T09:01:42.000Z","section":"WORLD","sources":[{"name":"The New York Times — World","host":"nytimes.com","url":"https://nytimes.com/2026/07/19/world/americas/argentines-already-losing-their-minds-brace-for-world-cup-final.html","time":"2026-07-19T09:01:42.000Z"}]},{"id":"6b69aad2c054f8a9","headline":"5 clever design tricks to make a small home look bigger","time":"2026-07-19T09:01:00.000Z","section":"TOP","sources":[{"name":"NPR — News","host":"npr.org","url":"https://npr.org/2026/07/19/nx-s1-5891817/5-clever-design-tricks-to-make-a-small-home-look-bigger","time":"2026-07-19T09:01:00.000Z"}]},{"id":"403248c53d80746c","headline":"The Case of the 3:30 Emails","time":"2026-07-19T09:00:54.000Z","section":"MONEY","sources":[{"name":"The New York Times — Business","host":"nytimes.com","url":"https://nytimes.com/2026/07/19/business/delayed-email-glitch.html","time":"2026-07-19T09:00:54.000Z"}]},{"id":"0e69057472a144fe","headline":"Step Into the ‘Zone of Genius’ (Before A.I. Takes Your Job)","time":"2026-07-19T09:00:48.000Z","section":"MONEY","sources":[{"name":"The New York Times — Business","host":"nytimes.com","url":"https://nytimes.com/2026/07/19/business/step-into-the-zone-of-genius-before-ai-takes-your-job.html","time":"2026-07-19T09:00:48.000Z"}]},{"id":"a8266caeadb9d53b","headline":"How to watch the World Cup final: what to expect and more","time":"2026-07-19T09:00:41.000Z","section":"TOP","sources":[{"name":"NBC News — Top Stories","host":"nbcnews.com","url":"https://nbcnews.com/sports/soccer/world-cup-final-2026-watch-time-channel-spain-argentina-what-know-rcna588157","time":"2026-07-19T09:00:41.000Z"}]},{"id":"44a69e70d9a33d11","headline":"Politicians Are Trying to Change What Chatbots Say About Them","time":"2026-07-19T09:00:38.000Z","section":"POLITICS","sources":[{"name":"The New York Times — Politics","host":"nytimes.com","url":"https://nytimes.com/2026/07/19/us/politics/chatbots-political-campaigns.html","time":"2026-07-19T09:00:38.000Z"}]},{"id":"d721a5ceb6919eb9","headline":"Sibling Therapy Is on the Rise. Could It Help My Relationship With My Brother?","time":"2026-07-19T09:00:31.000Z","section":"HEALTH","sources":[{"name":"The New York Times — Health","host":"nytimes.com","url":"https://nytimes.com/2026/07/19/magazine/sibling-therapy.html","time":"2026-07-19T09:00:31.000Z"}]},{"id":"a80219e32e34cb2b","headline":"Trump Blasts ‘Sanctuary’ States, but Many Still Aid Deportations","time":"2026-07-19T09:00:24.000Z","section":"POLITICS","sources":[{"name":"The New York Times — Politics","host":"nytimes.com","url":"https://nytimes.com/2026/07/19/us/politics/sanctuary-states-deportation-aid.html","time":"2026-07-19T09:00:24.000Z"}]},{"id":"a367fbf13e2d1451","headline":"The ‘Bad Blood’ Between Polymarket’s Shayne Coplan and Kalshi’s Tarek Mansour","time":"2026-07-19T09:00:24.000Z","section":"MONEY","sources":[{"name":"The New York Times — Business","host":"nytimes.com","url":"https://nytimes.com/2026/07/19/technology/polymarket-kalshi-rivalry-coplan-mansour.html","time":"2026-07-19T09:00:24.000Z"}]},{"id":"169ec4b8bd744001","headline":"Restoring Britain’s health to 2014 levels could add 2% to GDP, thinktank says","time":"2026-07-19T09:00:22.000Z","section":"WORLD","sources":[{"name":"The Guardian — World","host":"theguardian.com","url":"https://theguardian.com/society/2026/jul/19/restoring-britains-health-to-2014-levels-could-add-2-to-gdp-thinktank-says","time":"2026-07-19T09:00:22.000Z"}]},{"id":"0d74139ffa681de1","headline":"Trump Gutted Civil Rights Agency, Stifling U.S. Scrutiny of Workplace Bias","time":"2026-07-19T09:00:13.000Z","section":"POLITICS","sources":[{"name":"The New York Times — Politics","host":"nytimes.com","url":"https://nytimes.com/2026/07/19/us/politics/trump-gutted-civil-rights-agency-stifling-us-scrutiny-of-workplace-bias.html","time":"2026-07-19T09:00:13.000Z"}]},{"id":"e15f9c8b758d5117","headline":"England beat France 6-4 to finish third","time":"2026-07-19T09:00:01.000Z","section":"WORLD","sources":[{"name":"France 24 — English","host":"france24.com","url":"https://france24.com/en/england-beat-france-6-4-to-finish-third","time":"2026-07-19T09:00:01.000Z"}]},{"id":"0d965c45c6bcf041","headline":"What Has the BBC Ever Done for Me?","time":"2026-07-19T09:00:00.000Z","section":"TOP","sources":[{"name":"BBC — Top Stories","host":"bbc.co.uk","url":"https://bbc.co.uk/iplayer/episodes/m002z1wj/watch/p0nyz55k?at_mid=AwZqPanva1&at_campaign=Making_The_Case_Trailer&at_medium=display_ad&at_campaign_type=owned&at_nation=NET&at_audience_id=SS&at_product=iplayer&at_brand=m002z1wj&at_ptr_name=bbc&at_ptr_type=media&at_format=image&at_objective=consumption&at_link_title=Making_The_Case_Trailer&at_bbc_team=BBC","time":"2026-07-19T09:00:00.000Z"}]},{"id":"e1dae4aac00eff94","headline":"French coach Didier Deschamps retires after 14 years","time":"2026-07-19T08:58:13.000Z","section":"WORLD","sources":[{"name":"France 24 — English","host":"france24.com","url":"https://france24.com/en/french-coach-didier-deschamps-retires-after-14-years","time":"2026-07-19T08:58:13.000Z"}]},{"id":"3c98bcab7691b629","headline":"Many carers hit with demands to repay more than £20,000 despite reforms","time":"2026-07-19T08:56:12.000Z","section":"WORLD","sources":[{"name":"The Guardian — World","host":"theguardian.com","url":"https://theguardian.com/society/2026/jul/18/scores-of-carers-overpaid-more-than-20000-last-year-despite-reforms","time":"2026-07-19T08:56:12.000Z"}]},{"id":"408576ea4a2ac49a","headline":"US: Taco Bell removes lettuce after parasite outbreak","time":"2026-07-19T08:55:21.000Z","section":"WORLD","sources":[{"name":"France 24 — English","host":"france24.com","url":"https://france24.com/en/us-taco-bell-removes-lettuce-after-parasite-outbreak","time":"2026-07-19T08:55:21.000Z"}]},{"id":"5baebd90ab81b806","headline":"Digital ID plan to be scrapped in Burnham's first major policy pledge","time":"2026-07-19T08:55:06.000Z","section":"TOP","sources":[{"name":"BBC — Top Stories","host":"bbc.co.uk","url":"https://bbc.co.uk/news/articles/c5y08z25q8eo?at_medium=RSS&at_campaign=rss","time":"2026-07-19T08:55:06.000Z"}]},{"id":"c2f3f7d875322422","headline":"First US soldiers killed in Jordan, Trump vows to shift action","time":"2026-07-19T08:52:59.000Z","section":"WORLD","sources":[{"name":"France 24 — English","host":"france24.com","url":"https://france24.com/en/first-us-soldiers-killed-in-jordan-trump-vows-to-shift-action","time":"2026-07-19T08:52:59.000Z"}]},{"id":"bb7fc3f1e54533bb","headline":"US launches new Iran strikes after two soldiers killed: What’s the latest?","time":"2026-07-19T08:49:56.000Z","section":"WORLD","sources":[{"name":"Al Jazeera — All","host":"aljazeera.com","url":"https://aljazeera.com/news/2026/7/19/us-launches-new-iran-strikes-after-two-soldiers-killed-whats-the-latest?traffic_source=rss","time":"2026-07-19T08:49:56.000Z"}]},{"id":"6d2635a96799ab77","headline":"From settlements to blocked recovery: Israeli strategy taking shape in Gaza","time":"2026-07-19T08:46:42.000Z","section":"WORLD","sources":[{"name":"Al Jazeera — All","host":"aljazeera.com","url":"https://aljazeera.com/news/2026/7/19/from-settlements-to-blocked-recovery-israeli-strategy-taking-shape-in-gaza?traffic_source=rss","time":"2026-07-19T08:46:42.000Z"}]},{"id":"8a88528a3a40f517","headline":"Spain fans bring the party to New York before World Cup final","time":"2026-07-19T08:41:18.000Z","section":"WORLD","sources":[{"name":"Al Jazeera — All","host":"aljazeera.com","url":"https://aljazeera.com/video/newsfeed/2026/7/19/spain-fans-bring-the-party-to-new-york-before-world-cup-final?traffic_source=rss","time":"2026-07-19T08:41:18.000Z"}]},{"id":"0a121eb164b6eb6c","headline":"A Modest Proposal for the Strait Dispute: A Shared Pact Among Gulf States","time":"2026-07-19T08:37:18.000Z","section":"WORLD","sources":[{"name":"The New York Times — World","host":"nytimes.com","url":"https://nytimes.com/2026/07/19/world/middleeast/strait-hormuz-iran.html","time":"2026-07-19T08:37:18.000Z"}]},{"id":"588e50dcc0601d91","headline":"Russia pounds Kyiv for five hours in one of its biggest ballistic missile attacks","time":"2026-07-19T08:35:16.000Z","section":"WORLD","sources":[{"name":"The Guardian — World","host":"theguardian.com","url":"https://theguardian.com/world/2026/jul/19/dozens-of-russian-missiles-pound-kyiv-ukraine-in-major-attack","time":"2026-07-19T08:35:16.000Z"}]},{"id":"969687936e2cf8e3","headline":"Spain vs Argentina: World Cup final predictions, schedule, Messi news","time":"2026-07-19T08:24:19.000Z","section":"WORLD","sources":[{"name":"Al Jazeera — All","host":"aljazeera.com","url":"https://aljazeera.com/news/2026/7/19/world-cup-final-2026-spain-argentina-predictions-schedule-messi?traffic_source=rss","time":"2026-07-19T08:24:19.000Z"}]},{"id":"b714bf74bc8166be","headline":"Perseid meteors to light up night sky in one of the year's most active showers","time":"2026-07-19T08:22:01.000Z","section":"SCIENCE","sources":[{"name":"BBC — Science & Environment","host":"bbc.co.uk","url":"https://bbc.co.uk/weather/articles/c7vg667m4y5o?at_medium=RSS&at_campaign=rss","time":"2026-07-19T08:22:01.000Z"}]},{"id":"816eab022d5c5bd4","headline":"Trump claims US World Cup a success, despite controversies, ahead of final","time":"2026-07-19T08:16:29.000Z","section":"WORLD","sources":[{"name":"© Jacquelyn Martin, AP","host":"france24.com","url":"https://france24.com/en/americas/20260719-trump-claims-us-world-cup-a-success-despite-controversies-ahead-of-final","time":"2026-07-19T08:16:29.000Z"}]},{"id":"86c656aaf47a65b0","headline":"2026 World Cup: France fall to England after wild ten-goal thriller","time":"2026-07-19T07:58:48.000Z","section":"WORLD","sources":[{"name":"France 24 — English","host":"france24.com","url":"https://france24.com/en/tv-shows/sports/20260719-2026-world-cup-france-fall-to-england-after-wild-ten-goal-thriller","time":"2026-07-19T07:58:48.000Z"}]},{"id":"bfcf43ef9ebddee4","headline":"Cuban dissident Luis Manuel Otero Alcántara goes into exile in US","time":"2026-07-19T07:47:02.000Z","section":"WORLD","sources":[{"name":"BBC — World","host":"bbc.co.uk","url":"https://bbc.co.uk/news/articles/cx2k77p2r1xo?at_medium=RSS&at_campaign=rss","time":"2026-07-19T07:47:02.000Z"}]},{"id":"fddb0b9efc7b6607","headline":"Cuban artist and dissident exiled from country after 5 years in prison arrives in US","time":"2026-07-19T07:27:59.000Z","section":"TOP","sources":[{"name":"NPR — News","host":"npr.org","url":"https://npr.org/2026/07/19/nx-s1-5899494/cuban-artist-exile-us","time":"2026-07-19T07:27:59.000Z"}]},{"id":"103975909d548884","headline":"Victoria announces new social media ‘demasking’ powers for accounts accused of vilification","time":"2026-07-19T07:22:01.000Z","section":"WORLD","sources":[{"name":"The Guardian — World","host":"theguardian.com","url":"https://theguardian.com/australia-news/2026/jul/19/victoria-proposes-social-media-account-identification-powers","time":"2026-07-19T07:22:01.000Z"}]},{"id":"b7c2797507c994e5","headline":"Ukraine’s Top General Becomes a Target of Protesters’ Anger","time":"2026-07-19T07:13:23.000Z","section":"WORLD","sources":[{"name":"The New York Times — World","host":"nytimes.com","url":"https://nytimes.com/2026/07/18/world/europe/ukraine-protests-general-syrskyi-fedorov.html","time":"2026-07-19T07:13:23.000Z"}]},{"id":"32fd23952fd0594d","headline":"MLS works to bring in a new generation of fans as the World Cup comes to an end","time":"2026-07-19T07:00:00.000Z","section":"TOP","sources":[{"name":"NPR — News","host":"npr.org","url":"https://npr.org/2026/07/19/nx-s1-5899020/2026-world-cup-fifa-mls-major-league-soccer","time":"2026-07-19T07:00:00.000Z"}]},{"id":"dce4ef65b449e6ce","headline":"'A 10-goal thriller': England fans react to 6-4 win over France","time":"2026-07-19T06:31:07.000Z","section":"WORLD","sources":[{"name":"BBC — UK","host":"bbc.co.uk","url":"https://bbc.co.uk/news/videos/cdj0337k0r7o?at_medium=RSS&at_campaign=rss","time":"2026-07-19T06:31:07.000Z"}]},{"id":"47abbedbc9ffc373","headline":"How new bird show hopes to help endangered flyers","time":"2026-07-19T06:24:07.000Z","section":"SCIENCE","sources":[{"name":"BBC — Science & Environment","host":"bbc.co.uk","url":"https://bbc.co.uk/news/articles/cly7z6gg9y6o?at_medium=RSS&at_campaign=rss","time":"2026-07-19T06:24:07.000Z"}]},{"id":"1acd9949801a2f99","headline":"Britain 'set for bumper year' for butterflies","time":"2026-07-19T06:14:19.000Z","section":"SCIENCE","sources":[{"name":"BBC — Science & Environment","host":"bbc.co.uk","url":"https://bbc.co.uk/news/articles/cwyml03r1e9o?at_medium=RSS&at_campaign=rss","time":"2026-07-19T06:14:19.000Z"}]},{"id":"8c7fd83a8091380b","headline":"I'll lose my bowel because my pain was dismissed until my husband spoke up","time":"2026-07-19T06:01:10.000Z","section":"WORLD","sources":[{"name":"BBC — UK","host":"bbc.co.uk","url":"https://bbc.co.uk/news/articles/c2047z42e7lo?at_medium=RSS&at_campaign=rss","time":"2026-07-19T06:01:10.000Z"}]},{"id":"d62c029511664bb9","headline":"‘We noticed a login from a new device’: the message from fraudsters targeting your X account","time":"2026-07-19T06:00:18.000Z","section":"TECH","sources":[{"name":"The Guardian — Technology","host":"theguardian.com","url":"https://theguardian.com/money/2026/jul/19/x-scams-login-new-device-message-account-crypto-phishing","time":"2026-07-19T06:00:18.000Z"}]},{"id":"58a4e626dbbbc6dd","headline":"Australian man detained by ICE in Los Angeles after earlier arrest attempt in Las Vegas","time":"2026-07-19T05:34:01.000Z","section":"US","sources":[{"name":"The Guardian — U.S.","host":"theguardian.com","url":"https://theguardian.com/australia-news/2026/jul/18/australian-man-detained-ice-los-angeles-arrest-attempt-las-vegas-airport","time":"2026-07-19T05:34:01.000Z"}]},{"id":"31c0e79b4403a05e","headline":"Terence Donovan, ‘larger-than-life’ actor and father of Jason, dies aged 90 – as it happened","time":"2026-07-19T05:32:35.000Z","section":"WORLD","sources":[{"name":"The Guardian — World","host":"theguardian.com","url":"https://theguardian.com/australia-news/live/2026/jul/19/anthony-albanese-labor-angus-taylor-coalition-pauline-hanson-bridget-mckenzie-cpac-london-politics-reactions-ski-field-temperature-high-diesel-prices-surge-ntwnfb","time":"2026-07-19T05:32:35.000Z"}]},{"id":"9187adea6672c3cf","headline":"‘We couldn’t let her story end there’: Virginia Roberts Giuffre’s brother on the year since her shocking death – and why he’s still fighting in her name","time":"2026-07-19T05:00:18.000Z","section":"US","sources":[{"name":"The Guardian — U.S.","host":"theguardian.com","url":"https://theguardian.com/us-news/2026/jul/19/virginia-giuffre-abuse-jeffrey-epstein-andrew-mountbatten-windsor-sky-roberts-brother-year-death","time":"2026-07-19T05:00:18.000Z"}]},{"id":"4ad5f006b042612b","headline":"Bank of England to stop accepting bonds linked to coal for key loans","time":"2026-07-19T05:00:17.000Z","section":"WORLD","sources":[{"name":"The Guardian — World","host":"theguardian.com","url":"https://theguardian.com/business/2026/jul/19/bank-of-england-bonds-coal-loans-assets","time":"2026-07-19T05:00:17.000Z"}]},{"id":"9850ddb6a78ee022","headline":"One week, two killings: Trump’s immigration crackdown turns deadly – again","time":"2026-07-19T05:00:17.000Z","section":"POLITICS","sources":[{"name":"The Guardian — U.S. Politics","host":"theguardian.com","url":"https://theguardian.com/news/ng-interactive/2026/jul/19/ice-killings-immigration-crackdown","time":"2026-07-19T05:00:17.000Z"}]},{"id":"c7b846ab8f5cc564","headline":"Here’s the latest.","time":"2026-07-19T04:46:28.000Z","section":"WORLD","sources":[{"name":"The New York Times — World","host":"nytimes.com","url":"https://nytimes.com/live/2026/07/18/world/iran-war-strikes-trump-hormuz/heres-the-latest","time":"2026-07-19T04:46:28.000Z"}]},{"id":"fc2f5b8aa2793d6e","headline":"Two US troops killed and one missing in Jordan after Iranian attacks","time":"2026-07-19T04:41:49.000Z","section":"WORLD","sources":[{"name":"The Guardian — World","host":"theguardian.com","url":"https://theguardian.com/world/2026/jul/18/iran-attacks-us-allies-in-middle-east-in-second-week-of-renewed-conflict","time":"2026-07-19T04:41:49.000Z"}]},{"id":"3cda5684df580151","headline":"In Maine, Troy Jackson Gains Momentum in Bid to Replace Platner","time":"2026-07-19T04:10:57.000Z","section":"POLITICS","sources":[{"name":"The New York Times — Politics","host":"nytimes.com","url":"https://nytimes.com/2026/07/19/us/politics/maine-democrats-senate-jackson.html","time":"2026-07-19T04:10:57.000Z"}]},{"id":"4cf678c33588509b","headline":"Why Tokyo’s New Shorts Policy is Sparking Debate in Japan","time":"2026-07-19T04:01:05.000Z","section":"WORLD","sources":[{"name":"The New York Times — World","host":"nytimes.com","url":"https://nytimes.com/2026/07/19/world/asia/japan-cool-biz-tokyo-shorts-heat.html","time":"2026-07-19T04:01:05.000Z"}]},{"id":"214f55be3a5fc100","headline":"São Tomé and Príncipe heads to polls in tense presidential election","time":"2026-07-19T04:00:16.000Z","section":"WORLD","sources":[{"name":"The Guardian — World","host":"theguardian.com","url":"https://theguardian.com/world/2026/jul/19/sao-tome-and-principe-presidential-election","time":"2026-07-19T04:00:16.000Z"}]},{"id":"106b97b9d9e20e1e","headline":"Argentina, Spain and their stars Lionel Messi and Lamine Yamal meet in World Cup final","time":"2026-07-19T04:00:00.000Z","section":"TOP","sources":[{"name":"NPR — News","host":"npr.org","url":"https://npr.org/2026/07/19/nx-s1-5899071/2026-world-cup-fifa-argentina-spain-final-championship","time":"2026-07-19T04:00:00.000Z"}]},{"id":"6e8ee91048c5dde8","headline":"Taylor Farms Expands Iceberg Lettuce Recall to 27 States Amid Cyclospora Outbreak","time":"2026-07-19T02:43:21.000Z","section":"SCIENCE","sources":[{"name":"The New York Times — Science","host":"nytimes.com","url":"https://nytimes.com/2026/07/18/health/taylor-farms-iceberg-lettuce-recall.html","time":"2026-07-19T02:43:21.000Z"}]},{"id":"6159c6d2097740c0","headline":"Inglaterra celebra el tercer lugar y Francia hace autocrítica tras la derrota","time":"2026-07-19T02:34:56.000Z","section":"TOP","sources":[{"name":"NBC News — Top Stories","host":"telemundo.com","url":"https://telemundo.com/deportes/copa-mundial-de-la-fifa-2026/video/inglaterra-celebra-el-tercer-lugar-y-francia-hace-autocritica-tras-la-derrota-tmvo13205176","time":"2026-07-19T02:34:56.000Z"}]},{"id":"17c95c2a1b4a5df8","headline":"Madison Square Garden Sues Wired Magazine Over L.G.B.T.Q. Tracking Report","time":"2026-07-19T02:34:10.000Z","section":"MONEY","sources":[{"name":"The New York Times — Business","host":"nytimes.com","url":"https://nytimes.com/2026/07/18/business/media/msg-entertainment-sues-wired-magazine.html","time":"2026-07-19T02:34:10.000Z"}]},{"id":"a4afa1bdaa658cdb","headline":"Tuchel destaca la respuesta de Inglaterra tras el golpe de semifinales","time":"2026-07-19T02:19:53.000Z","section":"TOP","sources":[{"name":"NBC News — Top Stories","host":"telemundo.com","url":"https://telemundo.com/deportes/copa-mundial-de-la-fifa-2026/video/tuchel-destaca-la-respuesta-de-inglaterra-tras-el-golpe-de-semifinales-tmvo13205172","time":"2026-07-19T02:19:53.000Z"}]},{"id":"a954c0206fdf28b5","headline":"Radar Mundial: Inglaterra conquista el tercer lugar tras un festival de diez goles","time":"2026-07-19T01:13:55.000Z","section":"TOP","sources":[{"name":"NBC News — Top Stories","host":"telemundo.com","url":"https://telemundo.com/deportes/copa-mundial-de-la-fifa-2026/video/radar-mundial-inglaterra-conquista-el-tercer-lugar-tras-un-festival-de-diez-goles-tmvo13205170","time":"2026-07-19T01:13:55.000Z"}]},{"id":"ad2cd12e73a9655e","headline":"Kylian Mbappé se convierte en el máximo goleador en la historia de los Mundiales","time":"2026-07-19T01:04:55.000Z","section":"TOP","sources":[{"name":"NBC News — Top Stories","host":"telemundo.com","url":"https://telemundo.com/deportes/copa-mundial-de-la-fifa-2026/video/kylian-mbappe-se-convierte-en-el-maximo-goleador-en-la-historia-de-los-mundiales-tmvo13205168","time":"2026-07-19T01:04:55.000Z"}]},{"id":"182959ae8f8571e5","headline":"Tempo coach Sandy Brondello suspended over ‘protected species’ comment about Angel Reese","time":"2026-07-19T01:02:55.000Z","section":"US","sources":[{"name":"The Guardian — U.S.","host":"theguardian.com","url":"https://theguardian.com/sport/2026/jul/18/sandy-brondello-suspended-angel-reese-protected-species-wnba-toronto-tempo","time":"2026-07-19T01:02:55.000Z"}]},{"id":"3689cb564397d362","headline":"Saka celebra el bronce y Mbappé deja la Bota de Oro en manos de Messi","time":"2026-07-19T00:59:14.000Z","section":"TOP","sources":[{"name":"NBC News — Top Stories","host":"telemundo.com","url":"https://telemundo.com/deportes/copa-mundial-de-la-fifa-2026/video/saka-celebra-el-bronce-y-mbappe-deja-la-bota-de-oro-en-manos-de-messi-tmvo13205166","time":"2026-07-19T00:59:14.000Z"}]},{"id":"8eac2c1116e8f855","headline":"Inglaterra y Francia regalaron un festival de goles en el duelo por el tercer lugar","time":"2026-07-19T00:58:54.000Z","section":"TOP","sources":[{"name":"NBC News — Top Stories","host":"telemundo.com","url":"https://telemundo.com/deportes/copa-mundial-de-la-fifa-2026/video/inglaterra-y-francia-regalaron-un-festival-de-goles-en-el-duelo-por-el-tercer-lugar-tmvo13205164","time":"2026-07-19T00:58:54.000Z"}]},{"id":"3955442de312d0a1","headline":"The Tate brothers are arrested in Miami, U.S. Marshals Service tells AP","time":"2026-07-19T00:57:08.000Z","section":"TOP","sources":[{"name":"NPR — News","host":"npr.org","url":"https://npr.org/2026/07/18/g-s1-134475/tate-brothers-arrested-miami","time":"2026-07-19T00:57:08.000Z"}]},{"id":"2d2c3f775b37bffe","headline":"Guti: “España no le tiene miedo a nadie” | Todo el Mundial","time":"2026-07-19T00:45:00.000Z","section":"TOP","sources":[{"name":"NBC News — Top Stories","host":"telemundo.com","url":"https://telemundo.com/deportes/copa-mundial-de-la-fifa-2026/video/guti-espana-no-le-tiene-miedo-a-nadie-todo-el-mundial-tmvo13205162","time":"2026-07-19T00:45:00.000Z"}]},{"id":"40fa90fb9388ce72","headline":"Miami vibra con el duelo por la medalla de bronce","time":"2026-07-19T00:38:08.000Z","section":"TOP","sources":[{"name":"NBC News — Top Stories","host":"telemundo.com","url":"https://telemundo.com/deportes/copa-mundial-de-la-fifa-2026/video/miami-vibra-con-el-duelo-por-la-medalla-de-bronce-tmvo13205158","time":"2026-07-19T00:38:08.000Z"}]},{"id":"eaf0767b561c0816","headline":"El Análisis Experto del partidazo entre Inglaterra y Francia por el tercer lugar del Mundial","time":"2026-07-19T00:36:52.000Z","section":"TOP","sources":[{"name":"NBC News — Top Stories","host":"telemundo.com","url":"https://telemundo.com/deportes/copa-mundial-de-la-fifa-2026/video/el-analisis-experto-del-partidazo-entre-inglaterra-y-francia-por-el-tercer-lugar-del-mundial-tmvo13205154","time":"2026-07-19T00:36:52.000Z"}]},{"id":"5c9038045a3d5e77","headline":"Tate brothers arrested by U.S. authorities, face additional rape charges in the U.K.","time":"2026-07-19T00:28:45.000Z","section":"TOP","sources":[{"name":"NBC News — Top Stories","host":"nbcnews.com","url":"https://nbcnews.com/world/united-kingdom/tate-brothers-arrested-us-face-additional-rape-charges-uk-rcna588210","time":"2026-07-19T00:28:45.000Z"}]},{"id":"7a43d0a462f1f523","headline":"El cuerpo técnico argentino explica qué hace a su selección especial | Todo el Mundial","time":"2026-07-19T00:26:14.000Z","section":"TOP","sources":[{"name":"NBC News — Top Stories","host":"telemundo.com","url":"https://telemundo.com/deportes/copa-mundial-de-la-fifa-2026/video/el-cuerpo-tecnico-argentino-explica-que-hace-a-su-seleccion-especial-todo-el-mundial-tmvo13205150","time":"2026-07-19T00:26:14.000Z"}]},{"id":"31df7f403d09f6eb","headline":"Adidas Hopes Its World Cup Moment Can Drive U.S. Sales","time":"2026-07-18T23:13:26.000Z","section":"MONEY","sources":[{"name":"The New York Times — Business","host":"nytimes.com","url":"https://nytimes.com/2026/07/18/business/adidas-world-cup-bjorn-gulden.html","time":"2026-07-18T23:13:26.000Z"}]},{"id":"c9fd0cff4b17da4b","headline":"Why Jordan Is Becoming a New Focus in the U.S.-Iran War","time":"2026-07-18T23:03:24.000Z","section":"WORLD","sources":[{"name":"The New York Times — World","host":"nytimes.com","url":"https://nytimes.com/2026/07/18/world/middleeast/iran-war-jordan-attacks.html","time":"2026-07-18T23:03:24.000Z"}]},{"id":"0321c03e98349efa","headline":"Cybersecurity risks posed by over-the-air tech in autos has analysts concerned","time":"2026-07-18T23:01:01.000Z","section":"MONEY","sources":[{"name":"CNBC — Business","host":"cnbc.com","url":"https://cnbc.com/2026/07/18/over-the-air-tech-in-vehicles-poses-cybersecurity-risks.html","time":"2026-07-18T23:01:01.000Z"}]},{"id":"680776695904f5af","headline":"America Caught World Cup Fever. His Job Is to Capitalize on It.","time":"2026-07-18T22:28:17.000Z","section":"MONEY","sources":[{"name":"The New York Times — Business","host":"nytimes.com","url":"https://nytimes.com/2026/07/18/business/dealbook/mls-don-garber-world-cup.html","time":"2026-07-18T22:28:17.000Z"}]},{"id":"564b482bfa5a8170","headline":"Taylor Farms recalls lettuce shipped to 27 states over cyclospora risk","time":"2026-07-18T22:26:59.000Z","section":"TOP","sources":[{"name":"PBS NewsHour — Headlines","host":"pbs.org","url":"https://pbs.org/newshour/health/taylor-farms-recalls-lettuce-shipped-to-27-states-over-cyclospora-risk","time":"2026-07-18T22:26:59.000Z"}]},{"id":"2ba659b57c1441f2","headline":"Cyclospora: iceberg lettuce recalled in 27 states and more products may follow","time":"2026-07-18T21:25:14.000Z","section":"US","sources":[{"name":"The Guardian — U.S.","host":"theguardian.com","url":"https://theguardian.com/us-news/2026/jul/18/cyclospora-iceberg-lettuce-recall","time":"2026-07-18T21:25:14.000Z"}]},{"id":"80c96a16f53f96a7","headline":"Darline Graham's career centered disability. Now she could help shape national policy","time":"2026-07-18T21:21:19.000Z","section":"TOP","sources":[{"name":"PBS NewsHour — Headlines","host":"pbs.org","url":"https://pbs.org/newshour/politics/darline-grahams-career-centered-disability-now-she-could-help-shape-national-policy","time":"2026-07-18T21:21:19.000Z"}]},{"id":"57ac74ea7f1be2e7","headline":"Oil tankers face 'worst case scenario' in Hormuz as Iran steps up attacks on ships, maritime risk CEO says","time":"2026-07-18T21:16:31.000Z","section":"MONEY","sources":[{"name":"CNBC — Business","host":"cnbc.com","url":"https://cnbc.com/2026/07/17/iran-war-oil-tanker-strait-hormuz-traffic-attacks-trump.html","time":"2026-07-18T21:16:31.000Z"}]},{"id":"ffe89fc99953417d","headline":"Cindy Burbank, Nebraska’s Democratic Senate Nominee, Files to Withdraw From Race","time":"2026-07-18T20:57:47.000Z","section":"POLITICS","sources":[{"name":"The New York Times — Politics","host":"nytimes.com","url":"https://nytimes.com/2026/07/18/us/politics/nebraska-senate-race-democrat-withdraw.html","time":"2026-07-18T20:57:47.000Z"}]},{"id":"7313dd5b678a3a7a","headline":"Nappy factor? New dad Sam Burns steals march on chasing pack to lead Open","time":"2026-07-18T20:33:32.000Z","section":"US","sources":[{"name":"The Guardian — U.S.","host":"theguardian.com","url":"https://theguardian.com/sport/2026/jul/18/new-dad-sam-burns-steals-march-on-chasing-pack-to-lead-open-after-third-day","time":"2026-07-18T20:33:32.000Z"}]},{"id":"50dbd7413ecd1a45","headline":"New York Mets reject concerns over in-game AI use after Ottavino claims","time":"2026-07-18T20:33:01.000Z","section":"US","sources":[{"name":"The Guardian — U.S.","host":"theguardian.com","url":"https://theguardian.com/sport/2026/jul/18/mets-andy-green-ai-strategy-mlb-compliance-ottavino-report","time":"2026-07-18T20:33:01.000Z"}]},{"id":"e48bb9cb470dfbcb","headline":"Eight released over alleged threat to Islamic event","time":"2026-07-18T20:29:25.000Z","section":"WORLD","sources":[{"name":"BBC — UK","host":"bbc.co.uk","url":"https://bbc.co.uk/news/articles/cr49xv56g77o?at_medium=RSS&at_campaign=rss","time":"2026-07-18T20:29:25.000Z"}]},{"id":"0775bae11353c1b7","headline":"Canada Wildfires: What to Know","time":"2026-07-18T20:16:59.000Z","section":"WORLD","sources":[{"name":"The New York Times — World","host":"nytimes.com","url":"https://nytimes.com/2026/07/18/world/canada/canada-wildfires-what-to-know.html","time":"2026-07-18T20:16:59.000Z"}]},{"id":"61e52291882f445d","headline":"27-year-old locksmith spent $7,000 on tools, works around the clock in NYC: 'I'd never held a screwdriver in my life' before starting","time":"2026-07-18T20:12:00.000Z","section":"MONEY","sources":[{"name":"CNBC — Business","host":"cnbc.com","url":"https://cnbc.com/2026/07/18/how-27-year-old-left-her-job-to-start-locksmith-girl-of-nyc.html","time":"2026-07-18T20:12:00.000Z"}]},{"id":"076e81556c8367b9","headline":"Josh Kerr of Britain breaks 27-year-old world record in the mile","time":"2026-07-18T20:06:35.000Z","section":"TOP","sources":[{"name":"NPR — News","host":"npr.org","url":"https://npr.org/2026/07/18/nx-s1-5899057/josh-kerr-mile-world-record-time","time":"2026-07-18T20:06:35.000Z"}]},{"id":"fcda079158efedaa","headline":"Thunderstorms will clear wildfire smoke from Northeast ahead of World Cup final, meteorologists say","time":"2026-07-18T20:02:57.000Z","section":"TOP","sources":[{"name":"PBS NewsHour — Headlines","host":"pbs.org","url":"https://pbs.org/newshour/nation/thunderstorms-will-clear-wildfire-smoke-from-northeast-ahead-of-world-cup-final-meteorologists-say","time":"2026-07-18T20:02:57.000Z"}]},{"id":"cf322e400e606ac6","headline":"ANU accused of ‘hysterical’ response to students using AI to cheat as unis scramble to ‘secure’ assessments","time":"2026-07-18T20:00:09.000Z","section":"TECH","sources":[{"name":"The Guardian — Technology","host":"theguardian.com","url":"https://theguardian.com/australia-news/2026/jul/18/anu-accused-of-hysterical-response-to-students-using-ai-to-as-unis-scramble-to-secure-assessments","time":"2026-07-18T20:00:09.000Z"}]},{"id":"66e1600c6aa66ddf","headline":"Walt Odets, Who Delved Into the Minds of Gay Men, Dies at 79","time":"2026-07-18T19:48:00.000Z","section":"HEALTH","sources":[{"name":"The New York Times — Health","host":"nytimes.com","url":"https://nytimes.com/2026/07/18/health/walt-odets-dead.html","time":"2026-07-18T19:48:00.000Z"}]},{"id":"f2e619d54ba3c70c","headline":"Hungary's president agrees to stand down after parliament backs removal","time":"2026-07-18T19:34:16.000Z","section":"WORLD","sources":[{"name":"BBC — World","host":"bbc.co.uk","url":"https://bbc.co.uk/news/articles/cpd7q7eev7po?at_medium=RSS&at_campaign=rss","time":"2026-07-18T19:34:16.000Z"}]},{"id":"ca4055b0aa630fc0","headline":"Republican lawmaker Ralph Norman to join race to succeed Lindsey Graham in South Carolina","time":"2026-07-18T19:14:03.000Z","section":"US","sources":[{"name":"The Guardian — U.S.","host":"theguardian.com","url":"https://theguardian.com/us-news/2026/jul/18/us-house-ralph-norman-south-carolina-lindsey-graham","time":"2026-07-18T19:14:03.000Z"}]},{"id":"4455618b423bf458","headline":"Korean beauty products are becoming mainstream in the U.S. Why there may be even more growth ahead","time":"2026-07-18T19:11:33.000Z","section":"MONEY","sources":[{"name":"CNBC — Business","host":"cnbc.com","url":"https://cnbc.com/2026/07/18/korean-beauty-products-are-becoming-mainstream-in-the-us.html","time":"2026-07-18T19:11:33.000Z"}]},{"id":"5b8bcd8a581c1e0a","headline":"U.S. cancels automatic protections for imperiled animals as critics warn of extinctions","time":"2026-07-18T18:43:58.000Z","section":"TOP","sources":[{"name":"PBS NewsHour — Headlines","host":"pbs.org","url":"https://pbs.org/newshour/nation/u-s-cancels-automatic-protections-for-imperiled-animals-as-critics-warn-of-extinctions","time":"2026-07-18T18:43:58.000Z"}]},{"id":"62b197bc61122a71","headline":"These AIPAC-Backed Democrats Voted to Nix Israel Aid. AIPAC Punished Them.","time":"2026-07-18T18:19:08.000Z","section":"POLITICS","sources":[{"name":"The New York Times — Politics","host":"nytimes.com","url":"https://nytimes.com/2026/07/18/us/politics/aipac-democrats-donations-israel-vote.html","time":"2026-07-18T18:19:08.000Z"}]},{"id":"db18dd49ff3907b2","headline":"David Crowley reenters battleground Wisconsin's Democratic governor primary with Gov. Evers' backing","time":"2026-07-18T18:17:43.000Z","section":"TOP","sources":[{"name":"PBS NewsHour — Headlines","host":"pbs.org","url":"https://pbs.org/newshour/politics/david-crowley-reenters-battleground-wisconsins-democratic-governor-primary-with-gov-evers-backing","time":"2026-07-18T18:17:43.000Z"}]},{"id":"f0dfc3e2278c7476","headline":"'WarshGPT': How Wall Street is adapting to the Fed's new era of communication","time":"2026-07-18T18:16:42.000Z","section":"MONEY","sources":[{"name":"CNBC — Business","host":"cnbc.com","url":"https://cnbc.com/2026/07/18/warshgpt-federal-reserve-communications-task-force-warsh.html","time":"2026-07-18T18:16:42.000Z"}]},{"id":"3c726a98d6ad78fd","headline":"Air quality improving in Northeast, while wildfire smoke hangs over Midwest","time":"2026-07-18T18:15:42.000Z","section":"TOP","sources":[{"name":"NPR — News","host":"npr.org","url":"https://npr.org/2026/07/18/nx-s1-5899009/us-canada-wildfire-smoke","time":"2026-07-18T18:15:42.000Z"}]},{"id":"db4120a7aff27d71","headline":"U.S. launches new airstrikes to 'punish' Iran for troop deaths","time":"2026-07-18T18:14:11.000Z","section":"WORLD","sources":[{"name":"NPR — World","host":"npr.org","url":"https://npr.org/2026/07/18/nx-s1-5899039/us-troops-killed-missing-iran-jordan","time":"2026-07-18T18:14:11.000Z"}]},{"id":"5521bcd167a6f4bc","headline":"Texas Hill Country floods test new warning systems after last year's deadly disaster","time":"2026-07-18T17:53:32.000Z","section":"TOP","sources":[{"name":"PBS NewsHour — Headlines","host":"pbs.org","url":"https://pbs.org/newshour/nation/texas-hill-country-floods-test-new-warning-systems-after-last-years-deadly-disaster","time":"2026-07-18T17:53:32.000Z"}]},{"id":"e4e446baad406189","headline":"Safety fears limit Ebola response in Congo, with more than 12 attacks on health facilities and workers recorded","time":"2026-07-18T17:34:04.000Z","section":"TOP","sources":[{"name":"PBS NewsHour — Headlines","host":"pbs.org","url":"https://pbs.org/newshour/world/safety-fears-limit-ebola-response-in-congo-with-more-than-12-attacks-on-health-facilities-and-workers-recorded","time":"2026-07-18T17:34:04.000Z"}]},{"id":"388199ff371b5a01","headline":"Trump threatens new Canada tariffs over fires sending 'filthy' air into US cities","time":"2026-07-18T17:29:50.000Z","section":"WORLD","sources":[{"name":"BBC — World","host":"bbc.co.uk","url":"https://bbc.co.uk/news/articles/cwyq93j34lgo?at_medium=RSS&at_campaign=rss","time":"2026-07-18T17:29:50.000Z"}]},{"id":"833b8ddc6ba392d9","headline":"Ukrainian drones hit warehouses and other sites across Russia, killing 9 and wounding over 60","time":"2026-07-18T17:21:36.000Z","section":"TOP","sources":[{"name":"PBS NewsHour — Headlines","host":"pbs.org","url":"https://pbs.org/newshour/world/ukrainian-drones-hit-warehouses-and-other-sites-across-russia-killing-9-and-wounding-over-60","time":"2026-07-18T17:21:36.000Z"}]},{"id":"c0a76d453f5b0dbc","headline":"Toronto, New York and Washington top list of most polluted cities as wildfires burn","time":"2026-07-18T17:18:47.000Z","section":"SCIENCE","sources":[{"name":"BBC — Science & Environment","host":"bbc.co.uk","url":"https://bbc.co.uk/news/articles/c5ywdl9ne3yo?at_medium=RSS&at_campaign=rss","time":"2026-07-18T17:18:47.000Z"}]},{"id":"387f13b9f98dee50","headline":"Woman killed while asleep with baby ‘was my world’, sister says","time":"2026-07-18T16:41:55.000Z","section":"WORLD","sources":[{"name":"BBC — UK","host":"bbc.co.uk","url":"https://bbc.co.uk/news/articles/cd0xzy2r1m7o?at_medium=RSS&at_campaign=rss","time":"2026-07-18T16:41:55.000Z"}]},{"id":"5bbf4892cffb7564","headline":"North Dakota men who discover they were switched as newborns sue hospital","time":"2026-07-18T16:23:09.000Z","section":"US","sources":[{"name":"The Guardian — U.S.","host":"theguardian.com","url":"https://theguardian.com/us-news/2026/jul/18/north-dakota-newborns-switched","time":"2026-07-18T16:23:09.000Z"}]},{"id":"bcbdc70ff3dc202e","headline":"First death reported in Legionnaires' disease outbreak in New York City","time":"2026-07-18T16:00:05.000Z","section":"TOP","sources":[{"name":"PBS NewsHour — Headlines","host":"pbs.org","url":"https://pbs.org/newshour/health/first-death-reported-in-legionnaires-disease-outbreak-in-new-york-city","time":"2026-07-18T16:00:05.000Z"}]},{"id":"480b94aa6cc74183","headline":"U.S. military launches new airstrikes to punish Iran for deaths of US troops","time":"2026-07-18T15:34:19.000Z","section":"TOP","sources":[{"name":"PBS NewsHour — Headlines","host":"pbs.org","url":"https://pbs.org/newshour/world/us-military-launches-new-airstrikes-to-punish-iran-for-deaths-of-us-troops","time":"2026-07-18T15:34:19.000Z"}]},{"id":"d5ad4f27c280348a","headline":"German politician resigns over surrogacy child controversy","time":"2026-07-18T15:23:31.000Z","section":"WORLD","sources":[{"name":"BBC — World","host":"bbc.co.uk","url":"https://bbc.co.uk/news/articles/cq56e9n1ddzo?at_medium=RSS&at_campaign=rss","time":"2026-07-18T15:23:31.000Z"}]},{"id":"4e3fce40e091e029","headline":"Wildfire smoke from Canada and Minnesota pushes farther into the U.S. and engulfs D.C. in haze","time":"2026-07-18T15:20:12.000Z","section":"TOP","sources":[{"name":"PBS NewsHour — Headlines","host":"pbs.org","url":"https://pbs.org/newshour/nation/wildfire-smoke-from-canada-and-minnesota-pushes-farther-into-the-u-s-and-engulfs-d-c-in-haze","time":"2026-07-18T15:20:12.000Z"}]},{"id":"222a8e656c714d4a","headline":"Burnham is 'people pleaser' with 'airy fairy' plans, says Kemi Badenoch","time":"2026-07-18T15:01:33.000Z","section":"WORLD","sources":[{"name":"BBC — UK","host":"bbc.co.uk","url":"https://bbc.co.uk/news/articles/c304l24m0leo?at_medium=RSS&at_campaign=rss","time":"2026-07-18T15:01:33.000Z"}]},{"id":"cdea1e301008e97f","headline":"Two unexpected revelations in Warren Buffett's CNBC interview","time":"2026-07-18T14:53:36.000Z","section":"MONEY","sources":[{"name":"CNBC — Business","host":"cnbc.com","url":"https://cnbc.com/2026/07/18/two-unexpected-revelations-in-warren-buffetts-cnbc-interview.html","time":"2026-07-18T14:53:36.000Z"}]},{"id":"98bd4ae5c0523cc9","headline":"Ruthless plotter? Flip-flopper? Dad dancer? Insiders reveal the real Andy Burnham","time":"2026-07-18T14:32:48.000Z","section":"WORLD","sources":[{"name":"BBC — UK","host":"bbc.co.uk","url":"https://bbc.co.uk/news/articles/c3043vl2l7zo?at_medium=RSS&at_campaign=rss","time":"2026-07-18T14:32:48.000Z"}]},{"id":"9249d71708722a28","headline":"UK tech advocates alarmed by Burnham plan to scrap technology department","time":"2026-07-18T13:42:43.000Z","section":"TECH","sources":[{"name":"The Guardian — Technology","host":"theguardian.com","url":"https://theguardian.com/politics/2026/jul/18/burnham-plan-to-scrap-technology-department-triggers-backlash","time":"2026-07-18T13:42:43.000Z"}]},{"id":"e2a393432016fba8","headline":"Roger Summit, Who Invented an Early Online Search Service, Dies at 95","time":"2026-07-18T13:24:48.000Z","section":"MONEY","sources":[{"name":"The New York Times — Business","host":"nytimes.com","url":"https://nytimes.com/2026/07/17/technology/roger-summit-dead.html","time":"2026-07-18T13:24:48.000Z"}]},{"id":"68562c8b46cf1d09","headline":"Zohran Mamdani Knows He Has Political Capital. And He Intends to Spend It.","time":"2026-07-18T13:24:37.000Z","section":"POLITICS","sources":[{"name":"The New York Times — Politics","host":"nytimes.com","url":"https://nytimes.com/2026/07/18/magazine/zohran-mamdani-interview.html","time":"2026-07-18T13:24:37.000Z"}]},{"id":"0d9c55ea5dc93073","headline":"I left the U.S. for Trinidad and Tobago: My family of 4 spends about $3,000 a month—and we've never been happier","time":"2026-07-18T13:00:01.000Z","section":"MONEY","sources":[{"name":"CNBC — Business","host":"cnbc.com","url":"https://cnbc.com/2026/07/18/i-left-the-us-for-trinidad-and-tobago-my-family-of-4-spends-3k-a-month-weve-never-been-happier.html","time":"2026-07-18T13:00:01.000Z"}]},{"id":"b8722687894bebe5","headline":"Why is it so hard for the U.S. to win wars?","time":"2026-07-18T12:45:13.000Z","section":"WORLD","sources":[{"name":"NPR — World","host":"npr.org","url":"https://npr.org/2026/07/18/g-s1-134037/why-is-it-so-hard-for-the-u-s-to-win-wars","time":"2026-07-18T12:45:13.000Z"}]},{"id":"48ee192f739502fb","headline":"The Evolution of Presidential Travel: Horse Carriages to Air Force One","time":"2026-07-18T12:32:43.000Z","section":"POLITICS","sources":[{"name":"The New York Times — Politics","host":"nytimes.com","url":"https://nytimes.com/2026/07/18/us/politics/trump-air-force-one-travel.html","time":"2026-07-18T12:32:43.000Z"}]},{"id":"a62d29812f87ec5e","headline":"Week in Politics: Trump's speech; midterm elections; Todd Blanche and Jay Clayton","time":"2026-07-18T11:42:09.000Z","section":"POLITICS","sources":[{"name":"NPR — Politics","host":"npr.org","url":"https://npr.org/2026/07/18/nx-s1-5894907/week-in-politics-trumps-speech-midterm-elections-todd-blanche-and-jay-clayton","time":"2026-07-18T11:42:09.000Z"}]},{"id":"6642d57d9f08415c","headline":"Why Locals Are Gatekeeping Their Favorite Places From Tourists","time":"2026-07-18T11:12:11.000Z","section":"MONEY","sources":[{"name":"The New York Times — Business","host":"nytimes.com","url":"https://nytimes.com/2026/07/18/travel/gatekeeping-tourism-mexico-city-milan.html","time":"2026-07-18T11:12:11.000Z"}]},{"id":"824a5c73fda86bb7","headline":"Laos says it can't determine cause of tourist deaths linked to methanol","time":"2026-07-18T11:10:20.000Z","section":"WORLD","sources":[{"name":"BBC — World","host":"bbc.co.uk","url":"https://bbc.co.uk/news/articles/cdx8rj99endo?at_medium=RSS&at_campaign=rss","time":"2026-07-18T11:10:20.000Z"}]},{"id":"95df18088552b6de","headline":"8 killed and more than 60 wounded in Ukrainian drone attack on Russian regions","time":"2026-07-18T10:45:43.000Z","section":"WORLD","sources":[{"name":"NPR — World","host":"npr.org","url":"https://npr.org/2026/07/18/nx-s1-5898963/8-killed-and-more-than-60-wounded-in-ukrainian-drone-attack-on-russian-regions","time":"2026-07-18T10:45:43.000Z"}]},{"id":"65d2fec508c12fb8","headline":"He spotted a sports relic in the thrift store. It’s about to make him rich.","time":"2026-07-18T10:00:01.000Z","section":"US","sources":[{"name":"The Washington Post — National","host":"washingtonpost.com","url":"https://washingtonpost.com/nation/2026/07/18/he-spotted-sports-relic-thrift-store-its-about-make-him-rich","time":"2026-07-18T10:00:01.000Z"}]},{"id":"57ed7b06874c34f9","headline":"Red wolves, once nearly wiped out, had a spring baby boom in North Carolina","time":"2026-07-18T10:00:01.000Z","section":"US","sources":[{"name":"The Washington Post — National","host":"washingtonpost.com","url":"https://washingtonpost.com/nation/2026/07/18/litters-red-wolves-born-nc-boosting-critically-endangered-population","time":"2026-07-18T10:00:01.000Z"}]}],"sources":[{"id":"gdelt-courts-indictments","label":"GDELT — Courts / Indictments","section":"COURTS","status":"error"},{"id":"gdelt-police-settlements","label":"GDELT — Police Settlements","section":"COURTS","status":"error"},{"id":"gdelt-public-corruption","label":"GDELT — Public Corruption","section":"COURTS","status":"error"},{"id":"gdelt-healthcare-fraud","label":"GDELT — Healthcare Fraud","section":"HEALTH","status":"error"},{"id":"pbs-health","label":"PBS NewsHour — Health","section":"HEALTH","status":"ok"},{"id":"nyt-health","label":"The New York Times — Health","section":"HEALTH","status":"ok"},{"id":"gdelt-local-government","label":"GDELT — Local Government","section":"LOCAL","status":"error"},{"id":"bbc-business","label":"BBC — Business","section":"MONEY","status":"ok"},{"id":"cnbc-business","label":"CNBC — Business","section":"MONEY","status":"ok"},{"id":"gdelt-contract-fraud","label":"GDELT — Contractor Fraud","section":"MONEY","status":"error"},{"id":"gdelt-public-money","label":"GDELT — Public Money Watch","section":"MONEY","status":"error"},{"id":"propublica-main","label":"ProPublica — Latest","section":"MONEY","status":"ok"},{"id":"nyt-business","label":"The New York Times — Business","section":"MONEY","status":"ok"},{"id":"npr-politics","label":"NPR — Politics","section":"POLITICS","status":"ok"},{"id":"pbs-politics","label":"PBS NewsHour — Politics","section":"POLITICS","status":"ok"},{"id":"politico-picks","label":"Politico — Picks","section":"POLITICS","status":"error"},{"id":"guardian-us-politics","label":"The Guardian — U.S. Politics","section":"POLITICS","status":"ok"},{"id":"nyt-politics","label":"The New York Times — Politics","section":"POLITICS","status":"ok"},{"id":"bbc-science","label":"BBC — Science & Environment","section":"SCIENCE","status":"ok"},{"id":"npr-science","label":"NPR — Science","section":"SCIENCE","status":"ok"},{"id":"pbs-science","label":"PBS NewsHour — Science","section":"SCIENCE","status":"ok"},{"id":"nyt-science","label":"The New York Times — Science","section":"SCIENCE","status":"ok"},{"id":"bbc-tech","label":"BBC — Technology","section":"TECH","status":"ok"},{"id":"guardian-tech","label":"The Guardian — Technology","section":"TECH","status":"ok"},{"id":"nyt-tech","label":"The New York Times — Technology","section":"TECH","status":"ok"},{"id":"bbc-top","label":"BBC — Top Stories","section":"TOP","status":"ok"},{"id":"nbc-top","label":"NBC News — Top Stories","section":"TOP","status":"ok"},{"id":"npr-news","label":"NPR — News","section":"TOP","status":"ok"},{"id":"pbs-headlines","label":"PBS NewsHour — Headlines","section":"TOP","status":"ok"},{"id":"gdelt-disasters","label":"GDELT — Disasters","section":"US","status":"error"},{"id":"guardian-us","label":"The Guardian — U.S.","section":"US","status":"ok"},{"id":"wapo-national","label":"The Washington Post — National","section":"US","status":"ok"},{"id":"usatoday-top","label":"USA Today — Top Stories","section":"US","status":"ok"},{"id":"gdelt-conflict","label":"GDELT — Conflict Watch","section":"WAR","status":"error"},{"id":"gdelt-war-frontline","label":"GDELT — War / Frontline","section":"WAR","status":"error"},{"id":"aljazeera-all","label":"Al Jazeera — All","section":"WORLD","status":"ok"},{"id":"bbc-uk","label":"BBC — UK","section":"WORLD","status":"ok"},{"id":"bbc-world","label":"BBC — World","section":"WORLD","status":"ok"},{"id":"france24-en","label":"France 24 — English","section":"WORLD","status":"ok"},{"id":"npr-world","label":"NPR — World","section":"WORLD","status":"ok"},{"id":"pbs-world","label":"PBS NewsHour — World","section":"WORLD","status":"ok"},{"id":"guardian-world","label":"The Guardian — World","section":"WORLD","status":"ok"},{"id":"nyt-world","label":"The New York Times — World","section":"WORLD","status":"ok"}]}